anyblok_postgres/__init__.py
anyblok_postgres/column.py
anyblok_postgres/materialized_view.py
anyblok_postgres/release.py
anyblok_postgres/tests/__init__.py
anyblok_postgres/tests/conftest.py
anyblok_postgres/tests/test_column.py
anyblok_postgres/tests/test_materialized_view.py
anyblok_postgres-1.0.0.dist-info/LICENSE.rst
anyblok_postgres-1.0.0.dist-info/METADATA
anyblok_postgres-1.0.0.dist-info/WHEEL
anyblok_postgres-1.0.0.dist-info/top_level.txt
anyblok_postgres-1.0.0.dist-info/RECORD
