Metadata-Version: 2.1
Name: anyblok-postgres
Version: 1.0.0
Summary: Versionned attachment for AnyBlok
Home-page: http://docs.anyblok-postgres.anyblok.org/1.0.0
Author: jssuzanne
Author-email: jssuzanne@anybox.fr
License: UNKNOWN
Keywords: anyblok postgres
Platform: UNKNOWN
Classifier: Development Status :: 2 - Pre-Alpha
Classifier: Intended Audience :: Developers
Classifier: Programming Language :: Python :: 3
Classifier: Programming Language :: Python :: 3.6
Classifier: Programming Language :: Python :: 3.7
Classifier: Programming Language :: Python :: 3.8
Classifier: Programming Language :: Python :: 3.9
Requires-Dist: anyblok (>=1.1.0)
